LICENSE
MANIFEST.in
README.rst
setup.cfg
setup.py
memorydb/LICENSE
memorydb/README.md
memorydb/__init__.py
memorydb/aggregate.py
memorydb/hamlet.py
memorydb/idgen.py
memorydb/memorydb.py
memorydb/test_aggregate.py
memorydb/test_idgen.py
memorydb/test_memorydb.py
memorydb/test_textanalysis.py
memorydb/text_analysis.py
memorydb.egg-info/PKG-INFO
memorydb.egg-info/SOURCES.txt
memorydb.egg-info/dependency_links.txt
memorydb.egg-info/top_level.txt