Metadata-Version: 1.1
Name: memorydb
Version: 1.2.1
Summary: Simple In-Memory Database for Python
Home-page: https://github.com/davidbetz/pymemorydb
Author: David Betz
Author-email: dfb@davidbetz.net
License: UNKNOWN
Keywords: database,in-memory database
Platform: UNKNOWN
Classifier: Intended Audience :: Developers
Classifier: Topic :: Software Development :: Build Tools
Classifier: License :: OSI Approved :: MIT License
Classifier: Programming Language :: Python :: 2.7
Classifier: Programming Language :: Python :: 3.6
